{
  "type" : "FeatureCollection",
  "features" : [ {
    "type" : "Feature",
    "geometry" : {
      "type" : "Point",
      "coordinates" : [ 60.5721325365, 56.891013545 ]
    },
    "properties" : {
      "type" : "place",
      "startTime" : "20131126T212424+0600",
      "endTime" : "20131127T080854+0600",
      "place" : {
        "id" : 65236298,
        "name" : "Home",
        "type" : "home",
        "location" : {
          "lat" : 56.891013545,
          "lon" : 60.5721325365
        }
      },
      "lastUpdate" : "20131127T040453Z",
      "date" : "20131127"
    }
  }, {
    "type" : "Feature",
    "geometry" : {
      "type" : "Point",
      "coordinates" : [ 60.5870730571, 56.9035639712 ]
    },
    "properties" : {
      "type" : "place",
      "startTime" : "20131127T081051+0600",
      "endTime" : "20131127T082059+0600",
      "place" : {
        "id" : 77451958,
        "type" : "unknown",
        "location" : {
          "lat" : 56.9035639712,
          "lon" : 60.5870730571
        }
      },
      "lastUpdate" : "20131127T040453Z",
      "date" : "20131127"
    }
  }, {
    "type" : "Feature",
    "geometry" : {
      "type" : "Point",
      "coordinates" : [ 60.61488940022382, 56.84156114616754 ]
    },
    "properties" : {
      "type" : "place",
      "startTime" : "20131127T085347+0600",
      "endTime" : "20131127T125740+0600",
      "place" : {
        "id" : 65245957,
        "name" : "УрФУ ИМКН (Матмех)",
        "type" : "user",
        "location" : {
          "lat" : 56.84156114616754,
          "lon" : 60.61488940022382
        }
      },
      "lastUpdate" : "20160602T083418Z",
      "date" : "20131127"
    }
  }, {
    "type" : "Feature",
    "geometry" : {
      "type" : "Point",
      "coordinates" : [ 60.59451541150879, 56.83715773828118 ]
    },
    "properties" : {
      "type" : "place",
      "startTime" : "20131127T132152+0600",
      "endTime" : "20131127T142014+0600",
      "place" : {
        "id" : 70827257,
        "name" : "Красный Леопард",
        "type" : "foursquare",
        "foursquareId" : "4de9e5b11f6e3ddebdbdd327",
        "location" : {
          "lat" : 56.83715773828118,
          "lon" : 60.59451541150879
        }
      },
      "lastUpdate" : "20131128T035550Z",
      "date" : "20131127"
    }
  }, {
    "type" : "Feature",
    "geometry" : {
      "type" : "Point",
      "coordinates" : [ 60.61488940022382, 56.84156114616754 ]
    },
    "properties" : {
      "type" : "place",
      "startTime" : "20131127T144221+0600",
      "endTime" : "20131127T155326+0600",
      "place" : {
        "id" : 65245957,
        "name" : "УрФУ ИМКН (Матмех)",
        "type" : "user",
        "location" : {
          "lat" : 56.84156114616754,
          "lon" : 60.61488940022382
        }
      },
      "lastUpdate" : "20160602T083418Z",
      "date" : "20131127"
    }
  }, {
    "type" : "Feature",
    "geometry" : {
      "type" : "Point",
      "coordinates" : [ 60.6120733442, 56.8391699851 ]
    },
    "properties" : {
      "type" : "place",
      "startTime" : "20131127T165629+0600",
      "endTime" : "20131127T170502+0600",
      "place" : {
        "id" : 77500418,
        "type" : "unknown",
        "location" : {
          "lat" : 56.8391699851,
          "lon" : 60.6120733442
        }
      },
      "lastUpdate" : "20131127T130038Z",
      "date" : "20131127"
    }
  }, {
    "type" : "Feature",
    "geometry" : {
      "type" : "Point",
      "coordinates" : [ 60.645647, 56.843468 ]
    },
    "properties" : {
      "type" : "place",
      "startTime" : "20131127T171026+0600",
      "endTime" : "20131127T172203+0600",
      "place" : {
        "id" : 70826944,
        "name" : "Трамвайная остановка \"УПИ\"",
        "type" : "foursquare",
        "foursquareId" : "4f97fbf2e4b04b2e5f9eb4a3",
        "location" : {
          "lat" : 56.843468,
          "lon" : 60.645647
        }
      },
      "lastUpdate" : "20131127T130038Z",
      "date" : "20131127"
    }
  }, {
    "type" : "Feature",
    "geometry" : {
      "type" : "Point",
      "coordinates" : [ 60.5721325365, 56.891013545 ]
    },
    "properties" : {
      "type" : "place",
      "startTime" : "20131127T182928+0600",
      "endTime" : "20131128T032913+0600",
      "place" : {
        "id" : 65236298,
        "name" : "Home",
        "type" : "home",
        "location" : {
          "lat" : 56.891013545,
          "lon" : 60.5721325365
        }
      },
      "lastUpdate" : "20131127T235219Z",
      "date" : "20131127"
    }
  } ]
}