{
  "type" : "FeatureCollection",
  "features" : [ {
    "type" : "Feature",
    "geometry" : {
      "type" : "Point",
      "coordinates" : [ 60.6148520947, 56.8319036536 ]
    },
    "properties" : {
      "type" : "place",
      "startTime" : "20151213T175421+0600",
      "endTime" : "20151214T145531+0600",
      "place" : {
        "id" : 276850773,
        "type" : "unknown",
        "location" : {
          "lat" : 56.8319036536,
          "lon" : 60.6148520947
        }
      },
      "lastUpdate" : "20151214T101202Z",
      "date" : "20151214"
    }
  }, {
    "type" : "Feature",
    "geometry" : {
      "type" : "Point",
      "coordinates" : [ 60.6172751906, 56.8396121191 ]
    },
    "properties" : {
      "type" : "place",
      "startTime" : "20151214T151010+0600",
      "endTime" : "20151214T152716+0600",
      "place" : {
        "id" : 65241987,
        "name" : "Кофехаус",
        "type" : "user",
        "location" : {
          "lat" : 56.8396121191,
          "lon" : 60.6172751906
        }
      },
      "lastUpdate" : "20151214T101202Z",
      "date" : "20151214"
    }
  }, {
    "type" : "Feature",
    "geometry" : {
      "type" : "Point",
      "coordinates" : [ 60.61488940022382, 56.84156114616754 ]
    },
    "properties" : {
      "type" : "place",
      "startTime" : "20151214T153200+0600",
      "endTime" : "20151214T211856+0600",
      "place" : {
        "id" : 65245957,
        "name" : "УрФУ ИМКН (Матмех)",
        "type" : "foursquare",
        "foursquareId" : "4f38d904e4b02a70e2b4ca7a",
        "location" : {
          "lat" : 56.84156114616754,
          "lon" : 60.61488940022382
        }
      },
      "lastUpdate" : "20151215T020032Z",
      "date" : "20151214"
    }
  }, {
    "type" : "Feature",
    "geometry" : {
      "type" : "Point",
      "coordinates" : [ 60.6148520947, 56.8319036536 ]
    },
    "properties" : {
      "type" : "place",
      "startTime" : "20151214T220032+0600",
      "endTime" : "20151215T103848+0600",
      "place" : {
        "id" : 276850773,
        "type" : "unknown",
        "location" : {
          "lat" : 56.8319036536,
          "lon" : 60.6148520947
        }
      },
      "lastUpdate" : "20151215T053858Z",
      "date" : "20151214"
    }
  } ]
}