{
  "type" : "FeatureCollection",
  "features" : [ {
    "type" : "Feature",
    "geometry" : {
      "type" : "Point",
      "coordinates" : [ 60.613080268, 56.8355184923 ]
    },
    "properties" : {
      "type" : "place",
      "startTime" : "20151124T223824+0600",
      "endTime" : "20151125T005749+0600",
      "place" : {
        "id" : 286202518,
        "type" : "unknown",
        "location" : {
          "lat" : 56.8355184923,
          "lon" : 60.613080268
        }
      },
      "lastUpdate" : "20151124T224802Z",
      "date" : "20151125"
    }
  }, {
    "type" : "Feature",
    "geometry" : {
      "type" : "Point",
      "coordinates" : [ 60.6142783207, 56.831926577 ]
    },
    "properties" : {
      "type" : "place",
      "startTime" : "20151125T024731+0600",
      "endTime" : "20151125T102444+0600",
      "place" : {
        "id" : 278463715,
        "type" : "unknown",
        "location" : {
          "lat" : 56.831926577,
          "lon" : 60.6142783207
        }
      },
      "lastUpdate" : "20151125T045156Z",
      "date" : "20151125"
    }
  }, {
    "type" : "Feature",
    "geometry" : {
      "type" : "Point",
      "coordinates" : [ 60.58612623391936, 56.82947461635581 ]
    },
    "properties" : {
      "type" : "place",
      "startTime" : "20151125T104931+0600",
      "endTime" : "20151125T160255+0600",
      "place" : {
        "id" : 267526997,
        "name" : "СКБ Контур",
        "type" : "user",
        "location" : {
          "lat" : 56.82947461635581,
          "lon" : 60.58612623391936
        }
      },
      "lastUpdate" : "20160516T162957Z",
      "date" : "20151125"
    }
  }, {
    "type" : "Feature",
    "geometry" : {
      "type" : "Point",
      "coordinates" : [ 60.61485888717678, 56.84078150685662 ]
    },
    "properties" : {
      "type" : "place",
      "startTime" : "20151125T164326+0600",
      "endTime" : "20151125T170137+0600",
      "place" : {
        "id" : 66103230,
        "name" : "Демидовский Зал",
        "type" : "foursquare",
        "foursquareId" : "51528e10e4b01a2c8f519b2d",
        "location" : {
          "lat" : 56.84078150685662,
          "lon" : 60.61485888717678
        }
      },
      "lastUpdate" : "20151125T132302Z",
      "date" : "20151125"
    }
  }, {
    "type" : "Feature",
    "geometry" : {
      "type" : "Point",
      "coordinates" : [ 60.61488940022382, 56.84156114616754 ]
    },
    "properties" : {
      "type" : "place",
      "startTime" : "20151125T170138+0600",
      "endTime" : "20151125T194507+0600",
      "place" : {
        "id" : 65245957,
        "name" : "УрФУ ИМКН (Матмех)",
        "type" : "foursquare",
        "foursquareId" : "4f38d904e4b02a70e2b4ca7a",
        "location" : {
          "lat" : 56.84156114616754,
          "lon" : 60.61488940022382
        }
      },
      "lastUpdate" : "20151125T145412Z",
      "date" : "20151125"
    }
  }, {
    "type" : "Feature",
    "geometry" : {
      "type" : "Point",
      "coordinates" : [ 60.6153290033, 56.8316409084 ]
    },
    "properties" : {
      "type" : "place",
      "startTime" : "20151125T200524+0600",
      "endTime" : "20151126T071153+0600",
      "place" : {
        "id" : 277165475,
        "type" : "unknown",
        "location" : {
          "lat" : 56.8316409084,
          "lon" : 60.6153290033
        }
      },
      "lastUpdate" : "20151126T013100Z",
      "date" : "20151125"
    }
  } ]
}