{
  "type" : "FeatureCollection",
  "features" : [ {
    "type" : "Feature",
    "geometry" : {
      "type" : "Point",
      "coordinates" : [ 60.5721325365, 56.891013545 ]
    },
    "properties" : {
      "type" : "place",
      "startTime" : "20140121T215638+0600",
      "endTime" : "20140122T134405+0600",
      "place" : {
        "id" : 65236298,
        "name" : "Home",
        "type" : "home",
        "location" : {
          "lat" : 56.891013545,
          "lon" : 60.5721325365
        }
      },
      "lastUpdate" : "20140122T105201Z",
      "date" : "20140122"
    }
  }, {
    "type" : "Feature",
    "geometry" : {
      "type" : "Point",
      "coordinates" : [ 60.61488940022382, 56.84156114616754 ]
    },
    "properties" : {
      "type" : "place",
      "startTime" : "20140122T144241+0600",
      "endTime" : "20140122T154344+0600",
      "place" : {
        "id" : 65245957,
        "name" : "УрФУ ИМКН (Матмех)",
        "type" : "foursquare",
        "foursquareId" : "4f38d904e4b02a70e2b4ca7a",
        "location" : {
          "lat" : 56.84156114616754,
          "lon" : 60.61488940022382
        }
      },
      "lastUpdate" : "20150923T053942Z",
      "date" : "20140122"
    }
  }, {
    "type" : "Feature",
    "geometry" : {
      "type" : "Point",
      "coordinates" : [ 60.618312549, 56.8399761567 ]
    },
    "properties" : {
      "type" : "place",
      "startTime" : "20140122T154345+0600",
      "endTime" : "20140122T162758+0600",
      "place" : {
        "id" : 79487537,
        "type" : "unknown",
        "location" : {
          "lat" : 56.8399761567,
          "lon" : 60.618312549
        }
      },
      "lastUpdate" : "20140122T120151Z",
      "date" : "20140122"
    }
  }, {
    "type" : "Feature",
    "geometry" : {
      "type" : "Point",
      "coordinates" : [ 60.5993050431, 56.836362756 ]
    },
    "properties" : {
      "type" : "place",
      "startTime" : "20140122T164910+0600",
      "endTime" : "20140122T165520+0600",
      "place" : {
        "id" : 70981726,
        "type" : "unknown",
        "location" : {
          "lat" : 56.836362756,
          "lon" : 60.5993050431
        }
      },
      "lastUpdate" : "20140122T120151Z",
      "date" : "20140122"
    }
  }, {
    "type" : "Feature",
    "geometry" : {
      "type" : "Point",
      "coordinates" : [ 60.61280071735382, 56.88756892148201 ]
    },
    "properties" : {
      "type" : "place",
      "startTime" : "20140122T170733+0600",
      "endTime" : "20140122T172224+0600",
      "place" : {
        "id" : 71375801,
        "name" : "Остановка «Метро Уралмаш»",
        "type" : "foursquare",
        "foursquareId" : "4d7e63df34468eec9989d293",
        "location" : {
          "lat" : 56.88756892148201,
          "lon" : 60.61280071735382
        }
      },
      "lastUpdate" : "20140122T120151Z",
      "date" : "20140122"
    }
  }, {
    "type" : "Feature",
    "geometry" : {
      "type" : "Point",
      "coordinates" : [ 60.5721325365, 56.891013545 ]
    },
    "properties" : {
      "type" : "place",
      "startTime" : "20140122T173333+0600",
      "endTime" : "20140123T115924+0600",
      "place" : {
        "id" : 65236298,
        "name" : "Home",
        "type" : "home",
        "location" : {
          "lat" : 56.891013545,
          "lon" : 60.5721325365
        }
      },
      "lastUpdate" : "20140123T072849Z",
      "date" : "20140122"
    }
  } ]
}