{
  "type" : "FeatureCollection",
  "features" : [ {
    "type" : "Feature",
    "geometry" : {
      "type" : "Point",
      "coordinates" : [ 60.6148520947, 56.8319036536 ]
    },
    "properties" : {
      "type" : "place",
      "startTime" : "20160125T152513+0600",
      "endTime" : "20160126T025331+0600",
      "place" : {
        "id" : 276850773,
        "type" : "unknown",
        "location" : {
          "lat" : 56.8319036536,
          "lon" : 60.6148520947
        }
      },
      "lastUpdate" : "20160125T214940Z",
      "date" : "20160126"
    }
  }, {
    "type" : "Feature",
    "geometry" : {
      "type" : "Point",
      "coordinates" : [ 60.6148520947, 56.8319036536 ]
    },
    "properties" : {
      "type" : "place",
      "startTime" : "20160126T025331+0600",
      "endTime" : "20160126T114627+0600",
      "place" : {
        "id" : 276850773,
        "type" : "unknown",
        "location" : {
          "lat" : 56.8319036536,
          "lon" : 60.6148520947
        }
      },
      "lastUpdate" : "20160126T062844Z",
      "date" : "20160126"
    }
  }, {
    "type" : "Feature",
    "geometry" : {
      "type" : "Point",
      "coordinates" : [ 60.61488940022382, 56.84156114616754 ]
    },
    "properties" : {
      "type" : "place",
      "startTime" : "20160126T120125+0600",
      "endTime" : "20160126T165007+0600",
      "place" : {
        "id" : 65245957,
        "name" : "УрФУ ИМКН (Матмех)",
        "type" : "foursquare",
        "foursquareId" : "4f38d904e4b02a70e2b4ca7a",
        "location" : {
          "lat" : 56.84156114616754,
          "lon" : 60.61488940022382
        }
      },
      "lastUpdate" : "20160126T112824Z",
      "date" : "20160126"
    }
  }, {
    "type" : "Feature",
    "geometry" : {
      "type" : "Point",
      "coordinates" : [ 60.623336508, 56.8399206774 ]
    },
    "properties" : {
      "type" : "place",
      "startTime" : "20160126T170117+0600",
      "endTime" : "20160126T170739+0600",
      "place" : {
        "id" : 301710569,
        "type" : "unknown",
        "location" : {
          "lat" : 56.8399206774,
          "lon" : 60.623336508
        }
      },
      "lastUpdate" : "20160126T112824Z",
      "date" : "20160126"
    }
  }, {
    "type" : "Feature",
    "geometry" : {
      "type" : "Point",
      "coordinates" : [ 60.61002971335657, 56.83937449142041 ]
    },
    "properties" : {
      "type" : "place",
      "startTime" : "20160126T172352+0600",
      "endTime" : "20160126T174736+0600",
      "place" : {
        "id" : 103871477,
        "name" : "Ленина, 41",
        "type" : "foursquare",
        "foursquareId" : "4f13b850e4b0f2c213b1ca28",
        "location" : {
          "lat" : 56.83937449142041,
          "lon" : 60.61002971335657
        }
      },
      "lastUpdate" : "20160126T124710Z",
      "date" : "20160126"
    }
  }, {
    "type" : "Feature",
    "geometry" : {
      "type" : "Point",
      "coordinates" : [ 60.58612623391936, 56.82947461635581 ]
    },
    "properties" : {
      "type" : "place",
      "startTime" : "20160126T180746+0600",
      "endTime" : "20160127T010621+0600",
      "place" : {
        "id" : 267526997,
        "name" : "СКБ Контур",
        "type" : "user",
        "location" : {
          "lat" : 56.82947461635581,
          "lon" : 60.58612623391936
        }
      },
      "lastUpdate" : "20160516T162957Z",
      "date" : "20160126"
    }
  } ]
}