{
  "type" : "FeatureCollection",
  "features" : [ {
    "type" : "Feature",
    "geometry" : {
      "type" : "Point",
      "coordinates" : [ 60.6148520947, 56.8319036536 ]
    },
    "properties" : {
      "type" : "place",
      "startTime" : "20151224T230729+0600",
      "endTime" : "20151225T135943+0600",
      "place" : {
        "id" : 276850773,
        "type" : "unknown",
        "location" : {
          "lat" : 56.8319036536,
          "lon" : 60.6148520947
        }
      },
      "lastUpdate" : "20151225T112931Z",
      "date" : "20151225"
    }
  }, {
    "type" : "Feature",
    "geometry" : {
      "type" : "Point",
      "coordinates" : [ 60.58612623391936, 56.82947461635581 ]
    },
    "properties" : {
      "type" : "place",
      "startTime" : "20151225T142149+0600",
      "endTime" : "20151225T213600+0600",
      "place" : {
        "id" : 267526997,
        "name" : "СКБ Контур",
        "type" : "user",
        "location" : {
          "lat" : 56.82947461635581,
          "lon" : 60.58612623391936
        }
      },
      "lastUpdate" : "20160516T162957Z",
      "date" : "20151225"
    }
  }, {
    "type" : "Feature",
    "geometry" : {
      "type" : "Point",
      "coordinates" : [ 60.6148361378, 56.8323195042 ]
    },
    "properties" : {
      "type" : "place",
      "startTime" : "20151225T215840+0600",
      "endTime" : "20151227T125302+0600",
      "place" : {
        "id" : 277165476,
        "type" : "unknown",
        "location" : {
          "lat" : 56.8323195042,
          "lon" : 60.6148361378
        }
      },
      "lastUpdate" : "20151227T121804Z",
      "date" : "20151225"
    }
  } ]
}