{
  "type" : "FeatureCollection",
  "features" : [ {
    "type" : "Feature",
    "geometry" : {
      "type" : "Point",
      "coordinates" : [ 60.6148520947, 56.8319036536 ]
    },
    "properties" : {
      "type" : "place",
      "startTime" : "20151224T220729+0500",
      "endTime" : "20151225T125943+0500",
      "place" : {
        "id" : 276850773,
        "type" : "unknown",
        "location" : {
          "lat" : 56.8319036536,
          "lon" : 60.6148520947
        }
      },
      "lastUpdate" : "20151225T112931Z",
      "date" : "20151225"
    }
  }, {
    "type" : "Feature",
    "geometry" : {
      "type" : "Point",
      "coordinates" : [ 60.58612623391936, 56.82947461635581 ]
    },
    "properties" : {
      "type" : "place",
      "startTime" : "20151225T132149+0500",
      "endTime" : "20151225T203600+0500",
      "place" : {
        "id" : 267526997,
        "name" : "СКБ Контур",
        "type" : "user",
        "location" : {
          "lat" : 56.82947461635581,
          "lon" : 60.58612623391936
        }
      },
      "lastUpdate" : "20160516T162957Z",
      "date" : "20151225"
    }
  }, {
    "type" : "Feature",
    "geometry" : {
      "type" : "Point",
      "coordinates" : [ 60.6148361378, 56.8323195042 ]
    },
    "properties" : {
      "type" : "place",
      "startTime" : "20151225T205840+0500",
      "endTime" : "20151227T115302+0500",
      "place" : {
        "id" : 277165476,
        "type" : "unknown",
        "location" : {
          "lat" : 56.8323195042,
          "lon" : 60.6148361378
        }
      },
      "lastUpdate" : "20151227T121804Z",
      "date" : "20151225"
    }
  } ]
}