{
  "type" : "FeatureCollection",
  "features" : [ {
    "type" : "Feature",
    "geometry" : {
      "type" : "Point",
      "coordinates" : [ 60.5721325365, 56.891013545 ]
    },
    "properties" : {
      "type" : "place",
      "startTime" : "20150927T001000+0500",
      "endTime" : "20150928T080910+0500",
      "place" : {
        "id" : 65236298,
        "name" : "Home",
        "type" : "home",
        "location" : {
          "lat" : 56.891013545,
          "lon" : 60.5721325365
        }
      },
      "lastUpdate" : "20150928T051338Z",
      "date" : "20150928"
    }
  }, {
    "type" : "Feature",
    "geometry" : {
      "type" : "Point",
      "coordinates" : [ 60.61280071735382, 56.88756892148201 ]
    },
    "properties" : {
      "type" : "place",
      "startTime" : "20150928T083502+0500",
      "endTime" : "20150928T084907+0500",
      "place" : {
        "id" : 71375801,
        "name" : "Остановка «Метро Уралмаш»",
        "type" : "foursquare",
        "foursquareId" : "4d7e63df34468eec9989d293",
        "location" : {
          "lat" : 56.88756892148201,
          "lon" : 60.61280071735382
        }
      },
      "lastUpdate" : "20150928T051338Z",
      "date" : "20150928"
    }
  }, {
    "type" : "Feature",
    "geometry" : {
      "type" : "Point",
      "coordinates" : [ 60.58612623391936, 56.82947461635581 ]
    },
    "properties" : {
      "type" : "place",
      "startTime" : "20150928T090559+0500",
      "endTime" : "20150928T140220+0500",
      "place" : {
        "id" : 267526997,
        "name" : "СКБ Контур",
        "type" : "user",
        "location" : {
          "lat" : 56.82947461635581,
          "lon" : 60.58612623391936
        }
      },
      "lastUpdate" : "20160516T162957Z",
      "date" : "20150928"
    }
  }, {
    "type" : "Feature",
    "geometry" : {
      "type" : "Point",
      "coordinates" : [ 60.61488940022382, 56.84156114616754 ]
    },
    "properties" : {
      "type" : "place",
      "startTime" : "20150928T142155+0500",
      "endTime" : "20150928T165043+0500",
      "place" : {
        "id" : 65245957,
        "name" : "УрФУ ИМКН (Матмех)",
        "type" : "user",
        "location" : {
          "lat" : 56.84156114616754,
          "lon" : 60.61488940022382
        }
      },
      "lastUpdate" : "20160602T083418Z",
      "date" : "20150928"
    }
  }, {
    "type" : "Feature",
    "geometry" : {
      "type" : "Point",
      "coordinates" : [ 60.58612623391936, 56.82947461635581 ]
    },
    "properties" : {
      "type" : "place",
      "startTime" : "20150928T173132+0500",
      "endTime" : "20150928T201909+0500",
      "place" : {
        "id" : 267526997,
        "name" : "СКБ Контур",
        "type" : "user",
        "location" : {
          "lat" : 56.82947461635581,
          "lon" : 60.58612623391936
        }
      },
      "lastUpdate" : "20160516T162957Z",
      "date" : "20150928"
    }
  }, {
    "type" : "Feature",
    "geometry" : {
      "type" : "Point",
      "coordinates" : [ 60.604477055, 56.8240698373 ]
    },
    "properties" : {
      "type" : "place",
      "startTime" : "20150928T204126+0500",
      "endTime" : "20150928T211640+0500",
      "place" : {
        "id" : 269436975,
        "type" : "unknown",
        "location" : {
          "lat" : 56.8240698373,
          "lon" : 60.604477055
        }
      },
      "lastUpdate" : "20150928T195959Z",
      "date" : "20150928"
    }
  }, {
    "type" : "Feature",
    "geometry" : {
      "type" : "Point",
      "coordinates" : [ 60.5721325365, 56.891013545 ]
    },
    "properties" : {
      "type" : "place",
      "startTime" : "20150928T225048+0500",
      "endTime" : "20150929T075901+0500",
      "place" : {
        "id" : 65236298,
        "name" : "Home",
        "type" : "home",
        "location" : {
          "lat" : 56.891013545,
          "lon" : 60.5721325365
        }
      },
      "lastUpdate" : "20150929T044240Z",
      "date" : "20150928"
    }
  } ]
}