{
  "type" : "FeatureCollection",
  "features" : [ {
    "type" : "Feature",
    "geometry" : {
      "type" : "Point",
      "coordinates" : [ 60.6142783207, 56.831926577 ]
    },
    "properties" : {
      "type" : "place",
      "startTime" : "20151125T014731+0500",
      "endTime" : "20151125T092444+0500",
      "place" : {
        "id" : 278463715,
        "type" : "unknown",
        "location" : {
          "lat" : 56.831926577,
          "lon" : 60.6142783207
        }
      },
      "lastUpdate" : "20151125T045156Z",
      "date" : "20151125"
    }
  }, {
    "type" : "Feature",
    "geometry" : {
      "type" : "Point",
      "coordinates" : [ 60.58612623391936, 56.82947461635581 ]
    },
    "properties" : {
      "type" : "place",
      "startTime" : "20151125T094931+0500",
      "endTime" : "20151125T150255+0500",
      "place" : {
        "id" : 267526997,
        "name" : "СКБ Контур",
        "type" : "user",
        "location" : {
          "lat" : 56.82947461635581,
          "lon" : 60.58612623391936
        }
      },
      "lastUpdate" : "20160516T162957Z",
      "date" : "20151125"
    }
  }, {
    "type" : "Feature",
    "geometry" : {
      "type" : "Point",
      "coordinates" : [ 60.61485888717678, 56.84078150685662 ]
    },
    "properties" : {
      "type" : "place",
      "startTime" : "20151125T154326+0500",
      "endTime" : "20151125T160137+0500",
      "place" : {
        "id" : 66103230,
        "name" : "Демидовский Зал",
        "type" : "foursquare",
        "foursquareId" : "51528e10e4b01a2c8f519b2d",
        "location" : {
          "lat" : 56.84078150685662,
          "lon" : 60.61485888717678
        }
      },
      "lastUpdate" : "20151125T132302Z",
      "date" : "20151125"
    }
  }, {
    "type" : "Feature",
    "geometry" : {
      "type" : "Point",
      "coordinates" : [ 60.61488940022382, 56.84156114616754 ]
    },
    "properties" : {
      "type" : "place",
      "startTime" : "20151125T160138+0500",
      "endTime" : "20151125T184507+0500",
      "place" : {
        "id" : 65245957,
        "name" : "УрФУ ИМКН (Матмех)",
        "type" : "user",
        "location" : {
          "lat" : 56.84156114616754,
          "lon" : 60.61488940022382
        }
      },
      "lastUpdate" : "20160602T083418Z",
      "date" : "20151125"
    }
  }, {
    "type" : "Feature",
    "geometry" : {
      "type" : "Point",
      "coordinates" : [ 60.6153290033, 56.8316409084 ]
    },
    "properties" : {
      "type" : "place",
      "startTime" : "20151125T190524+0500",
      "endTime" : "20151126T061153+0500",
      "place" : {
        "id" : 277165475,
        "type" : "unknown",
        "location" : {
          "lat" : 56.8316409084,
          "lon" : 60.6153290033
        }
      },
      "lastUpdate" : "20151126T013100Z",
      "date" : "20151125"
    }
  } ]
}