{
  "type" : "FeatureCollection",
  "features" : [ {
    "type" : "Feature",
    "geometry" : {
      "type" : "Point",
      "coordinates" : [ 60.6156645155, 56.8313899353 ]
    },
    "properties" : {
      "type" : "place",
      "startTime" : "20160303T195918+0500",
      "endTime" : "20160304T144328+0500",
      "place" : {
        "id" : 300930959,
        "type" : "unknown",
        "location" : {
          "lat" : 56.8313899353,
          "lon" : 60.6156645155
        }
      },
      "lastUpdate" : "20160304T124932Z",
      "date" : "20160304"
    }
  }, {
    "type" : "Feature",
    "geometry" : {
      "type" : "Point",
      "coordinates" : [ 60.61488940022382, 56.84156114616754 ]
    },
    "properties" : {
      "type" : "place",
      "startTime" : "20160304T145042+0500",
      "endTime" : "20160304T190824+0500",
      "place" : {
        "id" : 65245957,
        "name" : "УрФУ ИМКН (Матмех)",
        "type" : "user",
        "location" : {
          "lat" : 56.84156114616754,
          "lon" : 60.61488940022382
        }
      },
      "lastUpdate" : "20160602T083418Z",
      "date" : "20160304"
    }
  }, {
    "type" : "Feature",
    "geometry" : {
      "type" : "Point",
      "coordinates" : [ 60.6143, 56.8323 ]
    },
    "properties" : {
      "type" : "place",
      "startTime" : "20160304T192412+0500",
      "endTime" : "20160305T123439+0500",
      "place" : {
        "id" : 278156785,
        "name" : "Home",
        "type" : "home",
        "location" : {
          "lat" : 56.8323,
          "lon" : 60.6143
        }
      },
      "lastUpdate" : "20170225T080940Z",
      "date" : "20160304"
    }
  } ]
}