{
  "type" : "FeatureCollection",
  "features" : [ {
    "type" : "Feature",
    "geometry" : {
      "type" : "Point",
      "coordinates" : [ 60.5721325365, 56.891013545 ]
    },
    "properties" : {
      "type" : "place",
      "startTime" : "20160501T225607+0600",
      "endTime" : "20160502T112211+0600",
      "place" : {
        "id" : 65236298,
        "name" : "Home",
        "type" : "home",
        "location" : {
          "lat" : 56.891013545,
          "lon" : 60.5721325365
        }
      },
      "lastUpdate" : "20160502T072538Z",
      "date" : "20160502"
    }
  }, {
    "type" : "Feature",
    "geometry" : {
      "type" : "Point",
      "coordinates" : [ 60.6143, 56.8323 ]
    },
    "properties" : {
      "type" : "place",
      "startTime" : "20160502T123635+0600",
      "endTime" : "20160503T103157+0600",
      "place" : {
        "id" : 278156785,
        "name" : "Home",
        "type" : "home",
        "location" : {
          "lat" : 56.8323,
          "lon" : 60.6143
        }
      },
      "lastUpdate" : "20160531T040259Z",
      "date" : "20160502"
    }
  } ]
}