{
  "type" : "FeatureCollection",
  "features" : [ {
    "type" : "Feature",
    "geometry" : {
      "type" : "Point",
      "coordinates" : [ 60.614426136016846, 56.84015864764703 ]
    },
    "properties" : {
      "type" : "place",
      "startTime" : "20151126T204136+0500",
      "endTime" : "20151127T000230+0500",
      "place" : {
        "id" : 287155495,
        "name" : "Дом печати",
        "type" : "foursquare",
        "foursquareId" : "50ab6b92e4b09282e9d88318",
        "location" : {
          "lat" : 56.84015864764703,
          "lon" : 60.614426136016846
        }
      },
      "lastUpdate" : "20151128T062938Z",
      "date" : "20151127"
    }
  }, {
    "type" : "Feature",
    "geometry" : {
      "type" : "Point",
      "coordinates" : [ 60.6143, 56.8323 ]
    },
    "properties" : {
      "type" : "place",
      "startTime" : "20151127T001542+0500",
      "endTime" : "20151127T004129+0500",
      "place" : {
        "id" : 278156785,
        "name" : "Home",
        "type" : "home",
        "location" : {
          "lat" : 56.8323,
          "lon" : 60.6143
        }
      },
      "lastUpdate" : "20170225T080940Z",
      "date" : "20151127"
    }
  }, {
    "type" : "Feature",
    "geometry" : {
      "type" : "Point",
      "coordinates" : [ 60.6148520947, 56.8319036536 ]
    },
    "properties" : {
      "type" : "place",
      "startTime" : "20151127T015314+0500",
      "endTime" : "20151127T095155+0500",
      "place" : {
        "id" : 276850773,
        "type" : "unknown",
        "location" : {
          "lat" : 56.8319036536,
          "lon" : 60.6148520947
        }
      },
      "lastUpdate" : "20151127T062558Z",
      "date" : "20151127"
    }
  }, {
    "type" : "Feature",
    "geometry" : {
      "type" : "Point",
      "coordinates" : [ 60.61488940022382, 56.84156114616754 ]
    },
    "properties" : {
      "type" : "place",
      "startTime" : "20151127T100903+0500",
      "endTime" : "20151127T152140+0500",
      "place" : {
        "id" : 65245957,
        "name" : "УрФУ ИМКН (Матмех)",
        "type" : "user",
        "location" : {
          "lat" : 56.84156114616754,
          "lon" : 60.61488940022382
        }
      },
      "lastUpdate" : "20160602T083418Z",
      "date" : "20151127"
    }
  }, {
    "type" : "Feature",
    "geometry" : {
      "type" : "Point",
      "coordinates" : [ 60.6153679216, 56.8319677488 ]
    },
    "properties" : {
      "type" : "place",
      "startTime" : "20151127T154320+0500",
      "endTime" : "20151128T094311+0500",
      "place" : {
        "id" : 276475865,
        "type" : "unknown",
        "location" : {
          "lat" : 56.8319677488,
          "lon" : 60.6153679216
        }
      },
      "lastUpdate" : "20151128T061936Z",
      "date" : "20151127"
    }
  } ]
}