{
  "type" : "FeatureCollection",
  "features" : [ {
    "type" : "Feature",
    "geometry" : {
      "type" : "Point",
      "coordinates" : [ 60.6153290033, 56.8316409084 ]
    },
    "properties" : {
      "type" : "place",
      "startTime" : "20160522T174742+0500",
      "endTime" : "20160523T052233+0500",
      "place" : {
        "id" : 277165475,
        "type" : "unknown",
        "location" : {
          "lat" : 56.8316409084,
          "lon" : 60.6153290033
        }
      },
      "lastUpdate" : "20160523T010525Z",
      "date" : "20160523"
    }
  }, {
    "type" : "Feature",
    "geometry" : {
      "type" : "Point",
      "coordinates" : [ 60.589896, 56.830022 ]
    },
    "properties" : {
      "type" : "place",
      "startTime" : "20160523T053202+0500",
      "endTime" : "20160523T090252+0500",
      "place" : {
        "id" : 317449856,
        "type" : "unknown",
        "location" : {
          "lat" : 56.830022,
          "lon" : 60.589896
        }
      },
      "lastUpdate" : "20160523T102408Z",
      "date" : "20160523"
    }
  }, {
    "type" : "Feature",
    "geometry" : {
      "type" : "Point",
      "coordinates" : [ 60.58612623391936, 56.82947461635581 ]
    },
    "properties" : {
      "type" : "place",
      "startTime" : "20160523T090252+0500",
      "endTime" : "20160523T141049+0500",
      "place" : {
        "id" : 267526997,
        "name" : "СКБ Контур",
        "type" : "user",
        "location" : {
          "lat" : 56.82947461635581,
          "lon" : 60.58612623391936
        }
      },
      "lastUpdate" : "20160523T102408Z",
      "date" : "20160523"
    }
  }, {
    "type" : "Feature",
    "geometry" : {
      "type" : "Point",
      "coordinates" : [ 60.61108628692485, 56.83920305604998 ]
    },
    "properties" : {
      "type" : "place",
      "startTime" : "20160523T142620+0500",
      "endTime" : "20160523T163906+0500",
      "place" : {
        "id" : 283080836,
        "name" : "Red Cup",
        "type" : "foursquare",
        "foursquareId" : "54e2e10f498e1f5a1803605c",
        "location" : {
          "lat" : 56.83920305604998,
          "lon" : 60.61108628692485
        }
      },
      "lastUpdate" : "20160523T132542Z",
      "date" : "20160523"
    }
  }, {
    "type" : "Feature",
    "geometry" : {
      "type" : "Point",
      "coordinates" : [ 60.6143, 56.8323 ]
    },
    "properties" : {
      "type" : "place",
      "startTime" : "20160523T165456+0500",
      "endTime" : "20160523T191238+0500",
      "place" : {
        "id" : 278156785,
        "name" : "Home",
        "type" : "home",
        "location" : {
          "lat" : 56.8323,
          "lon" : 60.6143
        }
      },
      "lastUpdate" : "20170225T080940Z",
      "date" : "20160523"
    }
  }, {
    "type" : "Feature",
    "geometry" : {
      "type" : "Point",
      "coordinates" : [ 60.6026485918, 56.8311072836 ]
    },
    "properties" : {
      "type" : "place",
      "startTime" : "20160523T192800+0500",
      "endTime" : "20160523T195334+0500",
      "place" : {
        "id" : 283963002,
        "type" : "unknown",
        "location" : {
          "lat" : 56.8311072836,
          "lon" : 60.6026485918
        }
      },
      "lastUpdate" : "20160523T163521Z",
      "date" : "20160523"
    }
  }, {
    "type" : "Feature",
    "geometry" : {
      "type" : "Point",
      "coordinates" : [ 60.614360165, 56.8345535697 ]
    },
    "properties" : {
      "type" : "place",
      "startTime" : "20160523T203111+0500",
      "endTime" : "20160523T203939+0500",
      "place" : {
        "id" : 278380714,
        "type" : "unknown",
        "location" : {
          "lat" : 56.8345535697,
          "lon" : 60.614360165
        }
      },
      "lastUpdate" : "20160523T163521Z",
      "date" : "20160523"
    }
  }, {
    "type" : "Feature",
    "geometry" : {
      "type" : "Point",
      "coordinates" : [ 60.6143, 56.8323 ]
    },
    "properties" : {
      "type" : "place",
      "startTime" : "20160523T203940+0500",
      "endTime" : "20160524T084423+0500",
      "place" : {
        "id" : 278156785,
        "name" : "Home",
        "type" : "home",
        "location" : {
          "lat" : 56.8323,
          "lon" : 60.6143
        }
      },
      "lastUpdate" : "20170225T080940Z",
      "date" : "20160523"
    }
  } ]
}