{
  "type" : "FeatureCollection",
  "features" : [ {
    "type" : "Feature",
    "geometry" : {
      "type" : "Point",
      "coordinates" : [ 60.5721325365, 56.891013545 ]
    },
    "properties" : {
      "type" : "place",
      "startTime" : "20140906T230019+0600",
      "endTime" : "20140907T141923+0600",
      "place" : {
        "id" : 65236298,
        "name" : "Home",
        "type" : "home",
        "location" : {
          "lat" : 56.891013545,
          "lon" : 60.5721325365
        }
      },
      "lastUpdate" : "20140907T102250Z",
      "date" : "20140907"
    }
  }, {
    "type" : "Feature",
    "geometry" : {
      "type" : "Point",
      "coordinates" : [ 60.56988525390625, 56.890769958496094 ]
    },
    "properties" : {
      "type" : "place",
      "startTime" : "20140907T141924+0600",
      "endTime" : "20140907T142847+0600",
      "place" : {
        "id" : 65236285,
        "name" : "остановка Донбасская",
        "type" : "foursquare",
        "foursquareId" : "50a44859e4b03aa3ead8e695",
        "location" : {
          "lat" : 56.890769958496094,
          "lon" : 60.56988525390625
        }
      },
      "lastUpdate" : "20140907T102250Z",
      "date" : "20140907"
    }
  }, {
    "type" : "Feature",
    "geometry" : {
      "type" : "Point",
      "coordinates" : [ 60.6141151571, 56.8934269716 ]
    },
    "properties" : {
      "type" : "place",
      "startTime" : "20140907T143754+0600",
      "endTime" : "20140907T155933+0600",
      "place" : {
        "id" : 154383098,
        "type" : "unknown",
        "location" : {
          "lat" : 56.8934269716,
          "lon" : 60.6141151571
        }
      },
      "lastUpdate" : "20140907T120022Z",
      "date" : "20140907"
    }
  }, {
    "type" : "Feature",
    "geometry" : {
      "type" : "Point",
      "coordinates" : [ 60.5721325365, 56.891013545 ]
    },
    "properties" : {
      "type" : "place",
      "startTime" : "20140907T161808+0600",
      "endTime" : "20140908T135221+0600",
      "place" : {
        "id" : 65236298,
        "name" : "Home",
        "type" : "home",
        "location" : {
          "lat" : 56.891013545,
          "lon" : 60.5721325365
        }
      },
      "lastUpdate" : "20140908T153614Z",
      "date" : "20140907"
    }
  } ]
}