{
  "type" : "FeatureCollection",
  "features" : [ {
    "type" : "Feature",
    "geometry" : {
      "type" : "Point",
      "coordinates" : [ 60.5721325365, 56.891013545 ]
    },
    "properties" : {
      "type" : "place",
      "startTime" : "20140923T202858+0600",
      "endTime" : "20140924T094038+0600",
      "place" : {
        "id" : 65236298,
        "name" : "Home",
        "type" : "home",
        "location" : {
          "lat" : 56.891013545,
          "lon" : 60.5721325365
        }
      },
      "lastUpdate" : "20140924T052928Z",
      "date" : "20140924"
    }
  }, {
    "type" : "Feature",
    "geometry" : {
      "type" : "Point",
      "coordinates" : [ 60.61488940022382, 56.84156114616754 ]
    },
    "properties" : {
      "type" : "place",
      "startTime" : "20140924T102645+0600",
      "endTime" : "20140924T143532+0600",
      "place" : {
        "id" : 65245957,
        "name" : "УрФУ ИМКН (Матмех)",
        "type" : "user",
        "location" : {
          "lat" : 56.84156114616754,
          "lon" : 60.61488940022382
        }
      },
      "lastUpdate" : "20160602T083418Z",
      "date" : "20140924"
    }
  }, {
    "type" : "Feature",
    "geometry" : {
      "type" : "Point",
      "coordinates" : [ 60.618312549, 56.8399761567 ]
    },
    "properties" : {
      "type" : "place",
      "startTime" : "20140924T143533+0600",
      "endTime" : "20140924T150024+0600",
      "place" : {
        "id" : 79487537,
        "type" : "unknown",
        "location" : {
          "lat" : 56.8399761567,
          "lon" : 60.618312549
        }
      },
      "lastUpdate" : "20140924T140732Z",
      "date" : "20140924"
    }
  }, {
    "type" : "Feature",
    "geometry" : {
      "type" : "Point",
      "coordinates" : [ 60.61488940022382, 56.84156114616754 ]
    },
    "properties" : {
      "type" : "place",
      "startTime" : "20140924T150447+0600",
      "endTime" : "20140924T161111+0600",
      "place" : {
        "id" : 65245957,
        "name" : "УрФУ ИМКН (Матмех)",
        "type" : "user",
        "location" : {
          "lat" : 56.84156114616754,
          "lon" : 60.61488940022382
        }
      },
      "lastUpdate" : "20160602T083418Z",
      "date" : "20140924"
    }
  }, {
    "type" : "Feature",
    "geometry" : {
      "type" : "Point",
      "coordinates" : [ 60.5990505554, 56.8360045189 ]
    },
    "properties" : {
      "type" : "place",
      "startTime" : "20140924T162646+0600",
      "endTime" : "20140924T182010+0600",
      "place" : {
        "id" : 76438086,
        "type" : "unknown",
        "location" : {
          "lat" : 56.8360045189,
          "lon" : 60.5990505554
        }
      },
      "lastUpdate" : "20140924T153249Z",
      "date" : "20140924"
    }
  }, {
    "type" : "Feature",
    "geometry" : {
      "type" : "Point",
      "coordinates" : [ 60.5721325365, 56.891013545 ]
    },
    "properties" : {
      "type" : "place",
      "startTime" : "20140924T185240+0600",
      "endTime" : "20140925T094649+0600",
      "place" : {
        "id" : 65236298,
        "name" : "Home",
        "type" : "home",
        "location" : {
          "lat" : 56.891013545,
          "lon" : 60.5721325365
        }
      },
      "lastUpdate" : "20140925T112352Z",
      "date" : "20140924"
    }
  } ]
}