{
  "type" : "FeatureCollection",
  "features" : [ {
    "type" : "Feature",
    "geometry" : {
      "type" : "Point",
      "coordinates" : [ 60.6143, 56.8323 ]
    },
    "properties" : {
      "type" : "place",
      "startTime" : "20160327T203020+0600",
      "endTime" : "20160328T151325+0600",
      "place" : {
        "id" : 278156785,
        "name" : "Home",
        "type" : "home",
        "location" : {
          "lat" : 56.8323,
          "lon" : 60.6143
        }
      },
      "lastUpdate" : "20160531T040259Z",
      "date" : "20160328"
    }
  }, {
    "type" : "Feature",
    "geometry" : {
      "type" : "Point",
      "coordinates" : [ 60.61488940022382, 56.84156114616754 ]
    },
    "properties" : {
      "type" : "place",
      "startTime" : "20160328T152811+0600",
      "endTime" : "20160328T183836+0600",
      "place" : {
        "id" : 65245957,
        "name" : "УрФУ ИМКН (Матмех)",
        "type" : "foursquare",
        "foursquareId" : "4f38d904e4b02a70e2b4ca7a",
        "location" : {
          "lat" : 56.84156114616754,
          "lon" : 60.61488940022382
        }
      },
      "lastUpdate" : "20160328T131234Z",
      "date" : "20160328"
    }
  }, {
    "type" : "Feature",
    "geometry" : {
      "type" : "Point",
      "coordinates" : [ 60.6143, 56.8323 ]
    },
    "properties" : {
      "type" : "place",
      "startTime" : "20160328T185411+0600",
      "endTime" : "20160329T104231+0600",
      "place" : {
        "id" : 278156785,
        "name" : "Home",
        "type" : "home",
        "location" : {
          "lat" : 56.8323,
          "lon" : 60.6143
        }
      },
      "lastUpdate" : "20160531T040259Z",
      "date" : "20160328"
    }
  } ]
}