{
  "type" : "FeatureCollection",
  "features" : [ {
    "type" : "Feature",
    "geometry" : {
      "type" : "Point",
      "coordinates" : [ 60.5721325365, 56.891013545 ]
    },
    "properties" : {
      "type" : "place",
      "startTime" : "20140408T232036+0600",
      "endTime" : "20140409T081826+0600",
      "place" : {
        "id" : 65236298,
        "name" : "Home",
        "type" : "home",
        "location" : {
          "lat" : 56.891013545,
          "lon" : 60.5721325365
        }
      },
      "lastUpdate" : "20140409T035109Z",
      "date" : "20140409"
    }
  }, {
    "type" : "Feature",
    "geometry" : {
      "type" : "Point",
      "coordinates" : [ 60.61488940022382, 56.84156114616754 ]
    },
    "properties" : {
      "type" : "place",
      "startTime" : "20140409T090717+0600",
      "endTime" : "20140409T104726+0600",
      "place" : {
        "id" : 65245957,
        "name" : "УрФУ ИМКН (Матмех)",
        "type" : "foursquare",
        "foursquareId" : "4f38d904e4b02a70e2b4ca7a",
        "location" : {
          "lat" : 56.84156114616754,
          "lon" : 60.61488940022382
        }
      },
      "lastUpdate" : "20150923T053942Z",
      "date" : "20140409"
    }
  }, {
    "type" : "Feature",
    "geometry" : {
      "type" : "Point",
      "coordinates" : [ 60.5994714965, 56.8369050908 ]
    },
    "properties" : {
      "type" : "place",
      "startTime" : "20140409T110257+0600",
      "endTime" : "20140409T113909+0600",
      "place" : {
        "id" : 66735238,
        "type" : "unknown",
        "location" : {
          "lat" : 56.8369050908,
          "lon" : 60.5994714965
        }
      },
      "lastUpdate" : "20140409T113335Z",
      "date" : "20140409"
    }
  }, {
    "type" : "Feature",
    "geometry" : {
      "type" : "Point",
      "coordinates" : [ 60.5721325365, 56.891013545 ]
    },
    "properties" : {
      "type" : "place",
      "startTime" : "20140409T143257+0600",
      "endTime" : "20140410T081332+0600",
      "place" : {
        "id" : 65236298,
        "name" : "Home",
        "type" : "home",
        "location" : {
          "lat" : 56.891013545,
          "lon" : 60.5721325365
        }
      },
      "lastUpdate" : "20140410T104826Z",
      "date" : "20140409"
    }
  } ]
}