{
  "type" : "FeatureCollection",
  "features" : [ {
    "type" : "Feature",
    "geometry" : {
      "type" : "Point",
      "coordinates" : [ 60.6156645155, 56.8313899353 ]
    },
    "properties" : {
      "type" : "place",
      "startTime" : "20160303T205918+0600",
      "endTime" : "20160304T154328+0600",
      "place" : {
        "id" : 300930959,
        "type" : "unknown",
        "location" : {
          "lat" : 56.8313899353,
          "lon" : 60.6156645155
        }
      },
      "lastUpdate" : "20160304T124932Z",
      "date" : "20160304"
    }
  }, {
    "type" : "Feature",
    "geometry" : {
      "type" : "Point",
      "coordinates" : [ 60.61488940022382, 56.84156114616754 ]
    },
    "properties" : {
      "type" : "place",
      "startTime" : "20160304T155042+0600",
      "endTime" : "20160304T200824+0600",
      "place" : {
        "id" : 65245957,
        "name" : "УрФУ ИМКН (Матмех)",
        "type" : "foursquare",
        "foursquareId" : "4f38d904e4b02a70e2b4ca7a",
        "location" : {
          "lat" : 56.84156114616754,
          "lon" : 60.61488940022382
        }
      },
      "lastUpdate" : "20160304T155610Z",
      "date" : "20160304"
    }
  }, {
    "type" : "Feature",
    "geometry" : {
      "type" : "Point",
      "coordinates" : [ 60.6143, 56.8323 ]
    },
    "properties" : {
      "type" : "place",
      "startTime" : "20160304T202412+0600",
      "endTime" : "20160305T133439+0600",
      "place" : {
        "id" : 278156785,
        "name" : "Home",
        "type" : "home",
        "location" : {
          "lat" : 56.8323,
          "lon" : 60.6143
        }
      },
      "lastUpdate" : "20160531T040259Z",
      "date" : "20160304"
    }
  } ]
}