{
  "type" : "FeatureCollection",
  "features" : [ {
    "type" : "Feature",
    "geometry" : {
      "type" : "Point",
      "coordinates" : [ 60.5721325365, 56.891013545 ]
    },
    "properties" : {
      "type" : "place",
      "startTime" : "20150927T011000+0600",
      "endTime" : "20150928T090910+0600",
      "place" : {
        "id" : 65236298,
        "name" : "Home",
        "type" : "home",
        "location" : {
          "lat" : 56.891013545,
          "lon" : 60.5721325365
        }
      },
      "lastUpdate" : "20150928T051338Z",
      "date" : "20150928"
    }
  }, {
    "type" : "Feature",
    "geometry" : {
      "type" : "Point",
      "coordinates" : [ 60.61280071735382, 56.88756892148201 ]
    },
    "properties" : {
      "type" : "place",
      "startTime" : "20150928T093502+0600",
      "endTime" : "20150928T094907+0600",
      "place" : {
        "id" : 71375801,
        "name" : "Остановка «Метро Уралмаш»",
        "type" : "foursquare",
        "foursquareId" : "4d7e63df34468eec9989d293",
        "location" : {
          "lat" : 56.88756892148201,
          "lon" : 60.61280071735382
        }
      },
      "lastUpdate" : "20150928T051338Z",
      "date" : "20150928"
    }
  }, {
    "type" : "Feature",
    "geometry" : {
      "type" : "Point",
      "coordinates" : [ 60.58612623391936, 56.82947461635581 ]
    },
    "properties" : {
      "type" : "place",
      "startTime" : "20150928T100559+0600",
      "endTime" : "20150928T150220+0600",
      "place" : {
        "id" : 267526997,
        "name" : "СКБ Контур",
        "type" : "user",
        "location" : {
          "lat" : 56.82947461635581,
          "lon" : 60.58612623391936
        }
      },
      "lastUpdate" : "20160516T162957Z",
      "date" : "20150928"
    }
  }, {
    "type" : "Feature",
    "geometry" : {
      "type" : "Point",
      "coordinates" : [ 60.61488940022382, 56.84156114616754 ]
    },
    "properties" : {
      "type" : "place",
      "startTime" : "20150928T152155+0600",
      "endTime" : "20150928T175043+0600",
      "place" : {
        "id" : 65245957,
        "name" : "УрФУ ИМКН (Матмех)",
        "type" : "foursquare",
        "foursquareId" : "4f38d904e4b02a70e2b4ca7a",
        "location" : {
          "lat" : 56.84156114616754,
          "lon" : 60.61488940022382
        }
      },
      "lastUpdate" : "20150928T133148Z",
      "date" : "20150928"
    }
  }, {
    "type" : "Feature",
    "geometry" : {
      "type" : "Point",
      "coordinates" : [ 60.58612623391936, 56.82947461635581 ]
    },
    "properties" : {
      "type" : "place",
      "startTime" : "20150928T183132+0600",
      "endTime" : "20150928T211909+0600",
      "place" : {
        "id" : 267526997,
        "name" : "СКБ Контур",
        "type" : "user",
        "location" : {
          "lat" : 56.82947461635581,
          "lon" : 60.58612623391936
        }
      },
      "lastUpdate" : "20160516T162957Z",
      "date" : "20150928"
    }
  }, {
    "type" : "Feature",
    "geometry" : {
      "type" : "Point",
      "coordinates" : [ 60.604477055, 56.8240698373 ]
    },
    "properties" : {
      "type" : "place",
      "startTime" : "20150928T214126+0600",
      "endTime" : "20150928T221640+0600",
      "place" : {
        "id" : 269436975,
        "type" : "unknown",
        "location" : {
          "lat" : 56.8240698373,
          "lon" : 60.604477055
        }
      },
      "lastUpdate" : "20150928T195959Z",
      "date" : "20150928"
    }
  }, {
    "type" : "Feature",
    "geometry" : {
      "type" : "Point",
      "coordinates" : [ 60.5721325365, 56.891013545 ]
    },
    "properties" : {
      "type" : "place",
      "startTime" : "20150928T235048+0600",
      "endTime" : "20150929T085901+0600",
      "place" : {
        "id" : 65236298,
        "name" : "Home",
        "type" : "home",
        "location" : {
          "lat" : 56.891013545,
          "lon" : 60.5721325365
        }
      },
      "lastUpdate" : "20150929T044240Z",
      "date" : "20150928"
    }
  } ]
}