{
  "type" : "FeatureCollection",
  "features" : [ {
    "type" : "Feature",
    "geometry" : {
      "type" : "Point",
      "coordinates" : [ 60.5721325365, 56.891013545 ]
    },
    "properties" : {
      "type" : "place",
      "startTime" : "20140225T190424+0600",
      "endTime" : "20140226T080214+0600",
      "place" : {
        "id" : 65236298,
        "name" : "Home",
        "type" : "home",
        "location" : {
          "lat" : 56.891013545,
          "lon" : 60.5721325365
        }
      },
      "lastUpdate" : "20140226T031443Z",
      "date" : "20140226"
    }
  }, {
    "type" : "Feature",
    "geometry" : {
      "type" : "Point",
      "coordinates" : [ 60.5774299359, 56.8975105035 ]
    },
    "properties" : {
      "type" : "place",
      "startTime" : "20140226T080805+0600",
      "endTime" : "20140226T082944+0600",
      "place" : {
        "id" : 78949575,
        "type" : "unknown",
        "location" : {
          "lat" : 56.8975105035,
          "lon" : 60.5774299359
        }
      },
      "lastUpdate" : "20140226T034455Z",
      "date" : "20140226"
    }
  }, {
    "type" : "Feature",
    "geometry" : {
      "type" : "Point",
      "coordinates" : [ 60.61488940022382, 56.84156114616754 ]
    },
    "properties" : {
      "type" : "place",
      "startTime" : "20140226T085902+0600",
      "endTime" : "20140226T121038+0600",
      "place" : {
        "id" : 65245957,
        "name" : "УрФУ ИМКН (Матмех)",
        "type" : "foursquare",
        "foursquareId" : "4f38d904e4b02a70e2b4ca7a",
        "location" : {
          "lat" : 56.84156114616754,
          "lon" : 60.61488940022382
        }
      },
      "lastUpdate" : "20150923T053942Z",
      "date" : "20140226"
    }
  }, {
    "type" : "Feature",
    "geometry" : {
      "type" : "Point",
      "coordinates" : [ 60.5721325365, 56.891013545 ]
    },
    "properties" : {
      "type" : "place",
      "startTime" : "20140226T130002+0600",
      "endTime" : "20140227T080303+0600",
      "place" : {
        "id" : 65236298,
        "name" : "Home",
        "type" : "home",
        "location" : {
          "lat" : 56.891013545,
          "lon" : 60.5721325365
        }
      },
      "lastUpdate" : "20140227T035857Z",
      "date" : "20140226"
    }
  } ]
}