{
  "type" : "FeatureCollection",
  "features" : [ {
    "type" : "Feature",
    "geometry" : {
      "type" : "Point",
      "coordinates" : [ 60.6148361378, 56.8323195042 ]
    },
    "properties" : {
      "type" : "place",
      "startTime" : "20151225T205840+0500",
      "endTime" : "20151227T115302+0500",
      "place" : {
        "id" : 277165476,
        "type" : "unknown",
        "location" : {
          "lat" : 56.8323195042,
          "lon" : 60.6148361378
        }
      },
      "lastUpdate" : "20151227T121804Z",
      "date" : "20151227"
    }
  }, {
    "type" : "Feature",
    "geometry" : {
      "type" : "Point",
      "coordinates" : [ 60.5721325365, 56.891013545 ]
    },
    "properties" : {
      "type" : "place",
      "startTime" : "20151227T124248+0500",
      "endTime" : "20151227T153505+0500",
      "place" : {
        "id" : 65236298,
        "name" : "Home",
        "type" : "home",
        "location" : {
          "lat" : 56.891013545,
          "lon" : 60.5721325365
        }
      },
      "lastUpdate" : "20151227T121804Z",
      "date" : "20151227"
    }
  }, {
    "type" : "Feature",
    "geometry" : {
      "type" : "Point",
      "coordinates" : [ 60.6153679216, 56.8319677488 ]
    },
    "properties" : {
      "type" : "place",
      "startTime" : "20151227T164131+0500",
      "endTime" : "20151228T110240+0500",
      "place" : {
        "id" : 276475865,
        "type" : "unknown",
        "location" : {
          "lat" : 56.8319677488,
          "lon" : 60.6153679216
        }
      },
      "lastUpdate" : "20151228T080856Z",
      "date" : "20151227"
    }
  } ]
}