{
  "type" : "FeatureCollection",
  "features" : [ {
    "type" : "Feature",
    "geometry" : {
      "type" : "Point",
      "coordinates" : [ 60.5721325365, 56.891013545 ]
    },
    "properties" : {
      "type" : "place",
      "startTime" : "20131204T224922+0600",
      "endTime" : "20131205T082321+0600",
      "place" : {
        "id" : 65236298,
        "name" : "Home",
        "type" : "home",
        "location" : {
          "lat" : 56.891013545,
          "lon" : 60.5721325365
        }
      },
      "lastUpdate" : "20131205T122556Z",
      "date" : "20131205"
    }
  }, {
    "type" : "Feature",
    "geometry" : {
      "type" : "Point",
      "coordinates" : [ 60.61488940022382, 56.84156114616754 ]
    },
    "properties" : {
      "type" : "place",
      "startTime" : "20131205T092253+0600",
      "endTime" : "20131205T123823+0600",
      "place" : {
        "id" : 65245957,
        "name" : "УрФУ ИМКН (Матмех)",
        "type" : "user",
        "location" : {
          "lat" : 56.84156114616754,
          "lon" : 60.61488940022382
        }
      },
      "lastUpdate" : "20160602T083418Z",
      "date" : "20131205"
    }
  }, {
    "type" : "Feature",
    "geometry" : {
      "type" : "Point",
      "coordinates" : [ 60.5992364849, 56.837701709 ]
    },
    "properties" : {
      "type" : "place",
      "startTime" : "20131205T125554+0600",
      "endTime" : "20131205T175735+0600",
      "place" : {
        "id" : 77225189,
        "type" : "unknown",
        "location" : {
          "lat" : 56.837701709,
          "lon" : 60.5992364849
        }
      },
      "lastUpdate" : "20131205T122609Z",
      "date" : "20131205"
    }
  }, {
    "type" : "Feature",
    "geometry" : {
      "type" : "Point",
      "coordinates" : [ 60.5721325365, 56.891013545 ]
    },
    "properties" : {
      "type" : "place",
      "startTime" : "20131205T185121+0600",
      "endTime" : "20131206T072859+0600",
      "place" : {
        "id" : 65236298,
        "name" : "Home",
        "type" : "home",
        "location" : {
          "lat" : 56.891013545,
          "lon" : 60.5721325365
        }
      },
      "lastUpdate" : "20131206T032800Z",
      "date" : "20131205"
    }
  } ]
}