{
  "type" : "FeatureCollection",
  "features" : [ {
    "type" : "Feature",
    "geometry" : {
      "type" : "Point",
      "coordinates" : [ 60.5721325365, 56.891013545 ]
    },
    "properties" : {
      "type" : "place",
      "startTime" : "20140226T130002+0600",
      "endTime" : "20140227T080303+0600",
      "place" : {
        "id" : 65236298,
        "name" : "Home",
        "type" : "home",
        "location" : {
          "lat" : 56.891013545,
          "lon" : 60.5721325365
        }
      },
      "lastUpdate" : "20140227T035857Z",
      "date" : "20140227"
    }
  }, {
    "type" : "Feature",
    "geometry" : {
      "type" : "Point",
      "coordinates" : [ 60.56988525390625, 56.890769958496094 ]
    },
    "properties" : {
      "type" : "place",
      "startTime" : "20140227T080642+0600",
      "endTime" : "20140227T081153+0600",
      "place" : {
        "id" : 65236285,
        "name" : "остановка Донбасская",
        "type" : "foursquare",
        "foursquareId" : "50a44859e4b03aa3ead8e695",
        "location" : {
          "lat" : 56.890769958496094,
          "lon" : 60.56988525390625
        }
      },
      "lastUpdate" : "20140227T035857Z",
      "date" : "20140227"
    }
  }, {
    "type" : "Feature",
    "geometry" : {
      "type" : "Point",
      "coordinates" : [ 60.61488940022382, 56.84156114616754 ]
    },
    "properties" : {
      "type" : "place",
      "startTime" : "20140227T090053+0600",
      "endTime" : "20140227T121330+0600",
      "place" : {
        "id" : 65245957,
        "name" : "УрФУ ИМКН (Матмех)",
        "type" : "foursquare",
        "foursquareId" : "4f38d904e4b02a70e2b4ca7a",
        "location" : {
          "lat" : 56.84156114616754,
          "lon" : 60.61488940022382
        }
      },
      "lastUpdate" : "20150923T053942Z",
      "date" : "20140227"
    }
  }, {
    "type" : "Feature",
    "geometry" : {
      "type" : "Point",
      "coordinates" : [ 60.61921119689942, 56.839683302424994 ]
    },
    "properties" : {
      "type" : "place",
      "startTime" : "20140227T122037+0600",
      "endTime" : "20140227T131006+0600",
      "place" : {
        "id" : 65246242,
        "name" : "Вилка-Ложка",
        "type" : "foursquare",
        "foursquareId" : "503b2e5fe4b0d42a5984875a",
        "location" : {
          "lat" : 56.839683302424994,
          "lon" : 60.61921119689942
        }
      },
      "lastUpdate" : "20140227T081901Z",
      "date" : "20140227"
    }
  }, {
    "type" : "Feature",
    "geometry" : {
      "type" : "Point",
      "coordinates" : [ 60.6141383865, 56.8419563375 ]
    },
    "properties" : {
      "type" : "place",
      "startTime" : "20140227T131852+0600",
      "endTime" : "20140227T141844+0600",
      "place" : {
        "id" : 65062140,
        "type" : "unknown",
        "location" : {
          "lat" : 56.8419563375,
          "lon" : 60.6141383865
        }
      },
      "lastUpdate" : "20140227T124959Z",
      "date" : "20140227"
    }
  }, {
    "type" : "Feature",
    "geometry" : {
      "type" : "Point",
      "coordinates" : [ 60.5721325365, 56.891013545 ]
    },
    "properties" : {
      "type" : "place",
      "startTime" : "20140227T150724+0600",
      "endTime" : "20140228T073613+0600",
      "place" : {
        "id" : 65236298,
        "name" : "Home",
        "type" : "home",
        "location" : {
          "lat" : 56.891013545,
          "lon" : 60.5721325365
        }
      },
      "lastUpdate" : "20140228T051607Z",
      "date" : "20140227"
    }
  } ]
}