{
  "type" : "FeatureCollection",
  "features" : [ {
    "type" : "Feature",
    "geometry" : {
      "type" : "Point",
      "coordinates" : [ 60.5721325365, 56.891013545 ]
    },
    "properties" : {
      "type" : "place",
      "startTime" : "20131205T185121+0600",
      "endTime" : "20131206T072859+0600",
      "place" : {
        "id" : 65236298,
        "name" : "Home",
        "type" : "home",
        "location" : {
          "lat" : 56.891013545,
          "lon" : 60.5721325365
        }
      },
      "lastUpdate" : "20131206T032800Z",
      "date" : "20131206"
    }
  }, {
    "type" : "Feature",
    "geometry" : {
      "type" : "Point",
      "coordinates" : [ 60.6059095706, 56.8962802648 ]
    },
    "properties" : {
      "type" : "place",
      "startTime" : "20131206T075053+0600",
      "endTime" : "20131206T081637+0600",
      "place" : {
        "id" : 78951965,
        "type" : "unknown",
        "location" : {
          "lat" : 56.8962802648,
          "lon" : 60.6059095706
        }
      },
      "lastUpdate" : "20131206T032800Z",
      "date" : "20131206"
    }
  }, {
    "type" : "Feature",
    "geometry" : {
      "type" : "Point",
      "coordinates" : [ 60.61488940022382, 56.84156114616754 ]
    },
    "properties" : {
      "type" : "place",
      "startTime" : "20131206T085851+0600",
      "endTime" : "20131206T094201+0600",
      "place" : {
        "id" : 65245957,
        "name" : "УрФУ ИМКН (Матмех)",
        "type" : "foursquare",
        "foursquareId" : "4f38d904e4b02a70e2b4ca7a",
        "location" : {
          "lat" : 56.84156114616754,
          "lon" : 60.61488940022382
        }
      },
      "lastUpdate" : "20150923T053942Z",
      "date" : "20131206"
    }
  }, {
    "type" : "Feature",
    "geometry" : {
      "type" : "Point",
      "coordinates" : [ 60.61921119689942, 56.839683302424994 ]
    },
    "properties" : {
      "type" : "place",
      "startTime" : "20131206T095920+0600",
      "endTime" : "20131206T122414+0600",
      "place" : {
        "id" : 65246242,
        "name" : "Вилка-Ложка",
        "type" : "foursquare",
        "foursquareId" : "503b2e5fe4b0d42a5984875a",
        "location" : {
          "lat" : 56.839683302424994,
          "lon" : 60.61921119689942
        }
      },
      "lastUpdate" : "20131206T075823Z",
      "date" : "20131206"
    }
  }, {
    "type" : "Feature",
    "geometry" : {
      "type" : "Point",
      "coordinates" : [ 60.61488940022382, 56.84156114616754 ]
    },
    "properties" : {
      "type" : "place",
      "startTime" : "20131206T123408+0600",
      "endTime" : "20131206T143738+0600",
      "place" : {
        "id" : 65245957,
        "name" : "УрФУ ИМКН (Матмех)",
        "type" : "foursquare",
        "foursquareId" : "4f38d904e4b02a70e2b4ca7a",
        "location" : {
          "lat" : 56.84156114616754,
          "lon" : 60.61488940022382
        }
      },
      "lastUpdate" : "20150923T053942Z",
      "date" : "20131206"
    }
  }, {
    "type" : "Feature",
    "geometry" : {
      "type" : "Point",
      "coordinates" : [ 60.6141383865, 56.8419563375 ]
    },
    "properties" : {
      "type" : "place",
      "startTime" : "20131206T144418+0600",
      "endTime" : "20131206T161617+0600",
      "place" : {
        "id" : 65062140,
        "type" : "unknown",
        "location" : {
          "lat" : 56.8419563375,
          "lon" : 60.6141383865
        }
      },
      "lastUpdate" : "20131206T122157Z",
      "date" : "20131206"
    }
  }, {
    "type" : "Feature",
    "geometry" : {
      "type" : "Point",
      "coordinates" : [ 60.5721325365, 56.891013545 ]
    },
    "properties" : {
      "type" : "place",
      "startTime" : "20131206T170526+0600",
      "endTime" : "20131206T183934+0600",
      "place" : {
        "id" : 65236298,
        "name" : "Home",
        "type" : "home",
        "location" : {
          "lat" : 56.891013545,
          "lon" : 60.5721325365
        }
      },
      "lastUpdate" : "20131206T152152Z",
      "date" : "20131206"
    }
  }, {
    "type" : "Feature",
    "geometry" : {
      "type" : "Point",
      "coordinates" : [ 60.591703493284555, 56.83850952313641 ]
    },
    "properties" : {
      "type" : "place",
      "startTime" : "20131206T192404+0600",
      "endTime" : "20131206T225810+0600",
      "place" : {
        "id" : 79472965,
        "name" : "Нирвана",
        "type" : "foursquare",
        "foursquareId" : "506effa0e4b06a580b48a6e1",
        "location" : {
          "lat" : 56.83850952313641,
          "lon" : 60.591703493284555
        }
      },
      "lastUpdate" : "20131209T042736Z",
      "date" : "20131206"
    }
  } ]
}