{
  "type" : "FeatureCollection",
  "features" : [ {
    "type" : "Feature",
    "geometry" : {
      "type" : "Point",
      "coordinates" : [ 60.5721325365, 56.891013545 ]
    },
    "properties" : {
      "type" : "place",
      "startTime" : "20131129T230346+0600",
      "endTime" : "20131130T165556+0600",
      "place" : {
        "id" : 65236298,
        "name" : "Home",
        "type" : "home",
        "location" : {
          "lat" : 56.891013545,
          "lon" : 60.5721325365
        }
      },
      "lastUpdate" : "20131130T151832Z",
      "date" : "20131130"
    }
  }, {
    "type" : "Feature",
    "geometry" : {
      "type" : "Point",
      "coordinates" : [ 60.56988525390625, 56.890769958496094 ]
    },
    "properties" : {
      "type" : "place",
      "startTime" : "20131130T165903+0600",
      "endTime" : "20131130T171443+0600",
      "place" : {
        "id" : 65236285,
        "name" : "остановка Донбасская",
        "type" : "foursquare",
        "foursquareId" : "50a44859e4b03aa3ead8e695",
        "location" : {
          "lat" : 56.890769958496094,
          "lon" : 60.56988525390625
        }
      },
      "lastUpdate" : "20131130T151832Z",
      "date" : "20131130"
    }
  }, {
    "type" : "Feature",
    "geometry" : {
      "type" : "Point",
      "coordinates" : [ 60.63626159651933, 56.84451215480135 ]
    },
    "properties" : {
      "type" : "place",
      "startTime" : "20131130T180014+0600",
      "endTime" : "20131130T205314+0600",
      "place" : {
        "id" : 78201188,
        "name" : "Глобус",
        "type" : "foursquare",
        "foursquareId" : "4f23ebe4e4b0085e496334e7",
        "location" : {
          "lat" : 56.84451215480135,
          "lon" : 60.63626159651933
        }
      },
      "lastUpdate" : "20131201T024227Z",
      "date" : "20131130"
    }
  }, {
    "type" : "Feature",
    "geometry" : {
      "type" : "Point",
      "coordinates" : [ 60.6318248876, 56.8419125578 ]
    },
    "properties" : {
      "type" : "place",
      "startTime" : "20131130T210058+0600",
      "endTime" : "20131130T210528+0600",
      "place" : {
        "id" : 69317326,
        "name" : "Клуб настольных игр \"Лепрекон\"",
        "type" : "user",
        "location" : {
          "lat" : 56.8419125578,
          "lon" : 60.6318248876
        }
      },
      "lastUpdate" : "20131130T164825Z",
      "date" : "20131130"
    }
  }, {
    "type" : "Feature",
    "geometry" : {
      "type" : "Point",
      "coordinates" : [ 60.5721325365, 56.891013545 ]
    },
    "properties" : {
      "type" : "place",
      "startTime" : "20131130T215528+0600",
      "endTime" : "20131201T131646+0600",
      "place" : {
        "id" : 65236298,
        "name" : "Home",
        "type" : "home",
        "location" : {
          "lat" : 56.891013545,
          "lon" : 60.5721325365
        }
      },
      "lastUpdate" : "20131201T111441Z",
      "date" : "20131130"
    }
  } ]
}