{
  "type" : "FeatureCollection",
  "features" : [ {
    "type" : "Feature",
    "geometry" : {
      "type" : "Point",
      "coordinates" : [ 60.6153679216, 56.8319677488 ]
    },
    "properties" : {
      "type" : "place",
      "startTime" : "20160411T204407+0500",
      "endTime" : "20160412T101354+0500",
      "place" : {
        "id" : 276475865,
        "type" : "unknown",
        "location" : {
          "lat" : 56.8319677488,
          "lon" : 60.6153679216
        }
      },
      "lastUpdate" : "20160412T062336Z",
      "date" : "20160412"
    }
  }, {
    "type" : "Feature",
    "geometry" : {
      "type" : "Point",
      "coordinates" : [ 60.61488940022382, 56.84156114616754 ]
    },
    "properties" : {
      "type" : "place",
      "startTime" : "20160412T103056+0500",
      "endTime" : "20160412T172450+0500",
      "place" : {
        "id" : 65245957,
        "name" : "УрФУ ИМКН (Матмех)",
        "type" : "user",
        "location" : {
          "lat" : 56.84156114616754,
          "lon" : 60.61488940022382
        }
      },
      "lastUpdate" : "20160602T083418Z",
      "date" : "20160412"
    }
  }, {
    "type" : "Feature",
    "geometry" : {
      "type" : "Point",
      "coordinates" : [ 60.61652898788452, 56.84045793598666 ]
    },
    "properties" : {
      "type" : "place",
      "startTime" : "20160412T172450+0500",
      "endTime" : "20160412T173223+0500",
      "place" : {
        "id" : 65297944,
        "name" : "Уральский федеральный университет имени первого Президента России Б.Н. Ельцина",
        "type" : "foursquare",
        "foursquareId" : "4c9fbb457c096dcb0e2de1d1",
        "location" : {
          "lat" : 56.84045793598666,
          "lon" : 60.61652898788452
        }
      },
      "lastUpdate" : "20160412T140952Z",
      "date" : "20160412"
    }
  }, {
    "type" : "Feature",
    "geometry" : {
      "type" : "Point",
      "coordinates" : [ 60.615326, 56.836223 ]
    },
    "properties" : {
      "type" : "place",
      "startTime" : "20160412T174135+0500",
      "endTime" : "20160412T174834+0500",
      "place" : {
        "id" : 321120174,
        "type" : "unknown",
        "location" : {
          "lat" : 56.836223,
          "lon" : 60.615326
        }
      },
      "lastUpdate" : "20160412T140952Z",
      "date" : "20160412"
    }
  }, {
    "type" : "Feature",
    "geometry" : {
      "type" : "Point",
      "coordinates" : [ 60.6143, 56.8323 ]
    },
    "properties" : {
      "type" : "place",
      "startTime" : "20160412T175814+0500",
      "endTime" : "20160412T180930+0500",
      "place" : {
        "id" : 278156785,
        "name" : "Home",
        "type" : "home",
        "location" : {
          "lat" : 56.8323,
          "lon" : 60.6143
        }
      },
      "lastUpdate" : "20170225T080940Z",
      "date" : "20160412"
    }
  }, {
    "type" : "Feature",
    "geometry" : {
      "type" : "Point",
      "coordinates" : [ 60.6176377064, 56.8325091153 ]
    },
    "properties" : {
      "type" : "place",
      "startTime" : "20160412T181812+0500",
      "endTime" : "20160412T182223+0500",
      "place" : {
        "id" : 299965218,
        "type" : "unknown",
        "location" : {
          "lat" : 56.8325091153,
          "lon" : 60.6176377064
        }
      },
      "lastUpdate" : "20160412T140953Z",
      "date" : "20160412"
    }
  }, {
    "type" : "Feature",
    "geometry" : {
      "type" : "Point",
      "coordinates" : [ 60.6153679216, 56.8319677488 ]
    },
    "properties" : {
      "type" : "place",
      "startTime" : "20160412T182938+0500",
      "endTime" : "20160413T101321+0500",
      "place" : {
        "id" : 276475865,
        "type" : "unknown",
        "location" : {
          "lat" : 56.8319677488,
          "lon" : 60.6153679216
        }
      },
      "lastUpdate" : "20160413T053345Z",
      "date" : "20160412"
    }
  } ]
}