{
  "type" : "FeatureCollection",
  "features" : [ {
    "type" : "Feature",
    "geometry" : {
      "type" : "Point",
      "coordinates" : [ 60.6148520947, 56.8319036536 ]
    },
    "properties" : {
      "type" : "place",
      "startTime" : "20151206T230012+0600",
      "endTime" : "20151207T095021+0600",
      "place" : {
        "id" : 276850773,
        "type" : "unknown",
        "location" : {
          "lat" : 56.8319036536,
          "lon" : 60.6148520947
        }
      },
      "lastUpdate" : "20151207T052409Z",
      "date" : "20151207"
    }
  }, {
    "type" : "Feature",
    "geometry" : {
      "type" : "Point",
      "coordinates" : [ 60.58612623391936, 56.82947461635581 ]
    },
    "properties" : {
      "type" : "place",
      "startTime" : "20151207T101518+0600",
      "endTime" : "20151207T160726+0600",
      "place" : {
        "id" : 267526997,
        "name" : "СКБ Контур",
        "type" : "user",
        "location" : {
          "lat" : 56.82947461635581,
          "lon" : 60.58612623391936
        }
      },
      "lastUpdate" : "20160516T162957Z",
      "date" : "20151207"
    }
  }, {
    "type" : "Feature",
    "geometry" : {
      "type" : "Point",
      "coordinates" : [ 60.6158219421, 56.8411201907 ]
    },
    "properties" : {
      "type" : "place",
      "startTime" : "20151207T164143+0600",
      "endTime" : "20151207T180110+0600",
      "place" : {
        "id" : 69449511,
        "type" : "unknown",
        "location" : {
          "lat" : 56.8411201907,
          "lon" : 60.6158219421
        }
      },
      "lastUpdate" : "20151207T160244Z",
      "date" : "20151207"
    }
  }, {
    "type" : "Feature",
    "geometry" : {
      "type" : "Point",
      "coordinates" : [ 60.6148520947, 56.8319036536 ]
    },
    "properties" : {
      "type" : "place",
      "startTime" : "20151207T181802+0600",
      "endTime" : "20151208T104344+0600",
      "place" : {
        "id" : 276850773,
        "type" : "unknown",
        "location" : {
          "lat" : 56.8319036536,
          "lon" : 60.6148520947
        }
      },
      "lastUpdate" : "20151208T060106Z",
      "date" : "20151207"
    }
  } ]
}