{
  "type" : "FeatureCollection",
  "features" : [ {
    "type" : "Feature",
    "geometry" : {
      "type" : "Point",
      "coordinates" : [ 60.6148520947, 56.8319036536 ]
    },
    "properties" : {
      "type" : "place",
      "startTime" : "20160124T182957+0500",
      "endTime" : "20160125T130532+0500",
      "place" : {
        "id" : 276850773,
        "type" : "unknown",
        "location" : {
          "lat" : 56.8319036536,
          "lon" : 60.6148520947
        }
      },
      "lastUpdate" : "20160125T094111Z",
      "date" : "20160125"
    }
  }, {
    "type" : "Feature",
    "geometry" : {
      "type" : "Point",
      "coordinates" : [ 60.61652898788452, 56.84045793598666 ]
    },
    "properties" : {
      "type" : "place",
      "startTime" : "20160125T132510+0500",
      "endTime" : "20160125T141151+0500",
      "place" : {
        "id" : 65297944,
        "name" : "Уральский федеральный университет имени первого Президента России Б.Н. Ельцина",
        "type" : "foursquare",
        "foursquareId" : "4c9fbb457c096dcb0e2de1d1",
        "location" : {
          "lat" : 56.84045793598666,
          "lon" : 60.61652898788452
        }
      },
      "lastUpdate" : "20160125T094111Z",
      "date" : "20160125"
    }
  }, {
    "type" : "Feature",
    "geometry" : {
      "type" : "Point",
      "coordinates" : [ 60.6148520947, 56.8319036536 ]
    },
    "properties" : {
      "type" : "place",
      "startTime" : "20160125T142513+0500",
      "endTime" : "20160126T015331+0500",
      "place" : {
        "id" : 276850773,
        "type" : "unknown",
        "location" : {
          "lat" : 56.8319036536,
          "lon" : 60.6148520947
        }
      },
      "lastUpdate" : "20160125T214940Z",
      "date" : "20160125"
    }
  } ]
}