{
  "type" : "FeatureCollection",
  "features" : [ {
    "type" : "Feature",
    "geometry" : {
      "type" : "Point",
      "coordinates" : [ 60.6148520947, 56.8319036536 ]
    },
    "properties" : {
      "type" : "place",
      "startTime" : "20151213T165421+0500",
      "endTime" : "20151214T135531+0500",
      "place" : {
        "id" : 276850773,
        "type" : "unknown",
        "location" : {
          "lat" : 56.8319036536,
          "lon" : 60.6148520947
        }
      },
      "lastUpdate" : "20151214T101202Z",
      "date" : "20151214"
    }
  }, {
    "type" : "Feature",
    "geometry" : {
      "type" : "Point",
      "coordinates" : [ 60.6172751906, 56.8396121191 ]
    },
    "properties" : {
      "type" : "place",
      "startTime" : "20151214T141010+0500",
      "endTime" : "20151214T142716+0500",
      "place" : {
        "id" : 65241987,
        "name" : "Кофехаус",
        "type" : "user",
        "location" : {
          "lat" : 56.8396121191,
          "lon" : 60.6172751906
        }
      },
      "lastUpdate" : "20151214T101202Z",
      "date" : "20151214"
    }
  }, {
    "type" : "Feature",
    "geometry" : {
      "type" : "Point",
      "coordinates" : [ 60.61488940022382, 56.84156114616754 ]
    },
    "properties" : {
      "type" : "place",
      "startTime" : "20151214T143200+0500",
      "endTime" : "20151214T201856+0500",
      "place" : {
        "id" : 65245957,
        "name" : "УрФУ ИМКН (Матмех)",
        "type" : "user",
        "location" : {
          "lat" : 56.84156114616754,
          "lon" : 60.61488940022382
        }
      },
      "lastUpdate" : "20160602T083418Z",
      "date" : "20151214"
    }
  }, {
    "type" : "Feature",
    "geometry" : {
      "type" : "Point",
      "coordinates" : [ 60.6148520947, 56.8319036536 ]
    },
    "properties" : {
      "type" : "place",
      "startTime" : "20151214T210032+0500",
      "endTime" : "20151215T093848+0500",
      "place" : {
        "id" : 276850773,
        "type" : "unknown",
        "location" : {
          "lat" : 56.8319036536,
          "lon" : 60.6148520947
        }
      },
      "lastUpdate" : "20151215T053858Z",
      "date" : "20151214"
    }
  } ]
}