{
  "type" : "FeatureCollection",
  "features" : [ {
    "type" : "Feature",
    "geometry" : {
      "type" : "Point",
      "coordinates" : [ 60.6148520947, 56.8319036536 ]
    },
    "properties" : {
      "type" : "place",
      "startTime" : "20151108T211811+0500",
      "endTime" : "20151109T081320+0500",
      "place" : {
        "id" : 276850773,
        "type" : "unknown",
        "location" : {
          "lat" : 56.8319036536,
          "lon" : 60.6148520947
        }
      },
      "lastUpdate" : "20151109T113816Z",
      "date" : "20151109"
    }
  }, {
    "type" : "Feature",
    "geometry" : {
      "type" : "Point",
      "coordinates" : [ 60.58612623391936, 56.82947461635581 ]
    },
    "properties" : {
      "type" : "place",
      "startTime" : "20151109T083958+0500",
      "endTime" : "20151109T140338+0500",
      "place" : {
        "id" : 267526997,
        "name" : "СКБ Контур",
        "type" : "user",
        "location" : {
          "lat" : 56.82947461635581,
          "lon" : 60.58612623391936
        }
      },
      "lastUpdate" : "20160516T162957Z",
      "date" : "20151109"
    }
  }, {
    "type" : "Feature",
    "geometry" : {
      "type" : "Point",
      "coordinates" : [ 60.61488940022382, 56.84156114616754 ]
    },
    "properties" : {
      "type" : "place",
      "startTime" : "20151109T144428+0500",
      "endTime" : "20151109T172341+0500",
      "place" : {
        "id" : 65245957,
        "name" : "УрФУ ИМКН (Матмех)",
        "type" : "user",
        "location" : {
          "lat" : 56.84156114616754,
          "lon" : 60.61488940022382
        }
      },
      "lastUpdate" : "20160602T083418Z",
      "date" : "20151109"
    }
  }, {
    "type" : "Feature",
    "geometry" : {
      "type" : "Point",
      "coordinates" : [ 60.6138876007, 56.8321437088 ]
    },
    "properties" : {
      "type" : "place",
      "startTime" : "20151109T174332+0500",
      "endTime" : "20151110T020236+0500",
      "place" : {
        "id" : 279249044,
        "type" : "unknown",
        "location" : {
          "lat" : 56.8321437088,
          "lon" : 60.6138876007
        }
      },
      "lastUpdate" : "20151110T041920Z",
      "date" : "20151109"
    }
  } ]
}