{
  "type" : "FeatureCollection",
  "features" : [ {
    "type" : "Feature",
    "geometry" : {
      "type" : "Point",
      "coordinates" : [ 60.6148361378, 56.8323195042 ]
    },
    "properties" : {
      "type" : "place",
      "startTime" : "20160212T235258+0600",
      "endTime" : "20160213T112612+0600",
      "place" : {
        "id" : 277165476,
        "type" : "unknown",
        "location" : {
          "lat" : 56.8323195042,
          "lon" : 60.6148361378
        }
      },
      "lastUpdate" : "20160213T082913Z",
      "date" : "20160213"
    }
  }, {
    "type" : "Feature",
    "geometry" : {
      "type" : "Point",
      "coordinates" : [ 60.58612623391936, 56.82947461635581 ]
    },
    "properties" : {
      "type" : "place",
      "startTime" : "20160213T115154+0600",
      "endTime" : "20160213T175628+0600",
      "place" : {
        "id" : 267526997,
        "name" : "СКБ Контур",
        "type" : "user",
        "location" : {
          "lat" : 56.82947461635581,
          "lon" : 60.58612623391936
        }
      },
      "lastUpdate" : "20160516T162957Z",
      "date" : "20160213"
    }
  }, {
    "type" : "Feature",
    "geometry" : {
      "type" : "Point",
      "coordinates" : [ 60.6148520947, 56.8319036536 ]
    },
    "properties" : {
      "type" : "place",
      "startTime" : "20160213T183015+0600",
      "endTime" : "20160215T105527+0600",
      "place" : {
        "id" : 276850773,
        "type" : "unknown",
        "location" : {
          "lat" : 56.8319036536,
          "lon" : 60.6148520947
        }
      },
      "lastUpdate" : "20160215T055112Z",
      "date" : "20160213"
    }
  } ]
}