{
  "type" : "FeatureCollection",
  "features" : [ {
    "type" : "Feature",
    "geometry" : {
      "type" : "Point",
      "coordinates" : [ 60.6148520947, 56.8319036536 ]
    },
    "properties" : {
      "type" : "place",
      "startTime" : "20151208T214556+0500",
      "endTime" : "20151209T150241+0500",
      "place" : {
        "id" : 276850773,
        "type" : "unknown",
        "location" : {
          "lat" : 56.8319036536,
          "lon" : 60.6148520947
        }
      },
      "lastUpdate" : "20151209T103555Z",
      "date" : "20151209"
    }
  }, {
    "type" : "Feature",
    "geometry" : {
      "type" : "Point",
      "coordinates" : [ 60.61485888717678, 56.84078150685662 ]
    },
    "properties" : {
      "type" : "place",
      "startTime" : "20151209T151926+0500",
      "endTime" : "20151209T152758+0500",
      "place" : {
        "id" : 66103230,
        "name" : "Демидовский Зал",
        "type" : "foursquare",
        "foursquareId" : "51528e10e4b01a2c8f519b2d",
        "location" : {
          "lat" : 56.84078150685662,
          "lon" : 60.61485888717678
        }
      },
      "lastUpdate" : "20151209T122341Z",
      "date" : "20151209"
    }
  }, {
    "type" : "Feature",
    "geometry" : {
      "type" : "Point",
      "coordinates" : [ 60.61488940022382, 56.84156114616754 ]
    },
    "properties" : {
      "type" : "place",
      "startTime" : "20151209T152759+0500",
      "endTime" : "20151209T200752+0500",
      "place" : {
        "id" : 65245957,
        "name" : "УрФУ ИМКН (Матмех)",
        "type" : "user",
        "location" : {
          "lat" : 56.84156114616754,
          "lon" : 60.61488940022382
        }
      },
      "lastUpdate" : "20160602T083418Z",
      "date" : "20151209"
    }
  }, {
    "type" : "Feature",
    "geometry" : {
      "type" : "Point",
      "coordinates" : [ 60.5919245979, 56.8235759904 ]
    },
    "properties" : {
      "type" : "place",
      "startTime" : "20151209T205243+0500",
      "endTime" : "20151209T222836+0500",
      "place" : {
        "id" : 279188582,
        "name" : "Home",
        "type" : "home",
        "location" : {
          "lat" : 56.8235759904,
          "lon" : 60.5919245979
        }
      },
      "lastUpdate" : "20151209T180130Z",
      "date" : "20151209"
    }
  }, {
    "type" : "Feature",
    "geometry" : {
      "type" : "Point",
      "coordinates" : [ 60.6142783207, 56.831926577 ]
    },
    "properties" : {
      "type" : "place",
      "startTime" : "20151209T230310+0500",
      "endTime" : "20151209T231949+0500",
      "place" : {
        "id" : 278463715,
        "type" : "unknown",
        "location" : {
          "lat" : 56.831926577,
          "lon" : 60.6142783207
        }
      },
      "lastUpdate" : "20151209T205350Z",
      "date" : "20151209"
    }
  }, {
    "type" : "Feature",
    "geometry" : {
      "type" : "Point",
      "coordinates" : [ 60.6148520947, 56.8319036536 ]
    },
    "properties" : {
      "type" : "place",
      "startTime" : "20151209T231949+0500",
      "endTime" : "20151210T083235+0500",
      "place" : {
        "id" : 276850773,
        "type" : "unknown",
        "location" : {
          "lat" : 56.8319036536,
          "lon" : 60.6148520947
        }
      },
      "lastUpdate" : "20151210T071533Z",
      "date" : "20151209"
    }
  } ]
}