{
  "type" : "FeatureCollection",
  "features" : [ {
    "type" : "Feature",
    "geometry" : {
      "type" : "Point",
      "coordinates" : [ 60.6148520947, 56.8319036536 ]
    },
    "properties" : {
      "type" : "place",
      "startTime" : "20151104T235548+0500",
      "endTime" : "20151105T073928+0500",
      "place" : {
        "id" : 276850773,
        "type" : "unknown",
        "location" : {
          "lat" : 56.8319036536,
          "lon" : 60.6148520947
        }
      },
      "lastUpdate" : "20151105T053055Z",
      "date" : "20151105"
    }
  }, {
    "type" : "Feature",
    "geometry" : {
      "type" : "Point",
      "coordinates" : [ 60.5893825707, 56.8294238576 ]
    },
    "properties" : {
      "type" : "place",
      "startTime" : "20151105T080113+0500",
      "endTime" : "20151105T081350+0500",
      "place" : {
        "id" : 280847967,
        "type" : "unknown",
        "location" : {
          "lat" : 56.8294238576,
          "lon" : 60.5893825707
        }
      },
      "lastUpdate" : "20151105T053055Z",
      "date" : "20151105"
    }
  }, {
    "type" : "Feature",
    "geometry" : {
      "type" : "Point",
      "coordinates" : [ 60.58612623391936, 56.82947461635581 ]
    },
    "properties" : {
      "type" : "place",
      "startTime" : "20151105T081351+0500",
      "endTime" : "20151105T135649+0500",
      "place" : {
        "id" : 267526997,
        "name" : "СКБ Контур",
        "type" : "user",
        "location" : {
          "lat" : 56.82947461635581,
          "lon" : 60.58612623391936
        }
      },
      "lastUpdate" : "20160516T162957Z",
      "date" : "20151105"
    }
  }, {
    "type" : "Feature",
    "geometry" : {
      "type" : "Point",
      "coordinates" : [ 60.61488940022382, 56.84156114616754 ]
    },
    "properties" : {
      "type" : "place",
      "startTime" : "20151105T143514+0500",
      "endTime" : "20151105T172032+0500",
      "place" : {
        "id" : 65245957,
        "name" : "УрФУ ИМКН (Матмех)",
        "type" : "user",
        "location" : {
          "lat" : 56.84156114616754,
          "lon" : 60.61488940022382
        }
      },
      "lastUpdate" : "20160602T083418Z",
      "date" : "20151105"
    }
  }, {
    "type" : "Feature",
    "geometry" : {
      "type" : "Point",
      "coordinates" : [ 60.58612623391936, 56.82947461635581 ]
    },
    "properties" : {
      "type" : "place",
      "startTime" : "20151105T175250+0500",
      "endTime" : "20151105T193753+0500",
      "place" : {
        "id" : 267526997,
        "name" : "СКБ Контур",
        "type" : "user",
        "location" : {
          "lat" : 56.82947461635581,
          "lon" : 60.58612623391936
        }
      },
      "lastUpdate" : "20160516T162957Z",
      "date" : "20151105"
    }
  }, {
    "type" : "Feature",
    "geometry" : {
      "type" : "Point",
      "coordinates" : [ 60.6148520947, 56.8319036536 ]
    },
    "properties" : {
      "type" : "place",
      "startTime" : "20151105T200218+0500",
      "endTime" : "20151106T085621+0500",
      "place" : {
        "id" : 276850773,
        "type" : "unknown",
        "location" : {
          "lat" : 56.8319036536,
          "lon" : 60.6148520947
        }
      },
      "lastUpdate" : "20151106T053036Z",
      "date" : "20151105"
    }
  } ]
}