{
  "type" : "FeatureCollection",
  "features" : [ {
    "type" : "Feature",
    "geometry" : {
      "type" : "Point",
      "coordinates" : [ 60.58612623391936, 56.82947461635581 ]
    },
    "properties" : {
      "type" : "place",
      "startTime" : "20160318T135120+0600",
      "endTime" : "20160319T001545+0600",
      "place" : {
        "id" : 267526997,
        "name" : "СКБ Контур",
        "type" : "user",
        "location" : {
          "lat" : 56.82947461635581,
          "lon" : 60.58612623391936
        }
      },
      "lastUpdate" : "20160516T162957Z",
      "date" : "20160319"
    }
  }, {
    "type" : "Feature",
    "geometry" : {
      "type" : "Point",
      "coordinates" : [ 60.6148520947, 56.8319036536 ]
    },
    "properties" : {
      "type" : "place",
      "startTime" : "20160319T004419+0600",
      "endTime" : "20160319T091949+0600",
      "place" : {
        "id" : 276850773,
        "type" : "unknown",
        "location" : {
          "lat" : 56.8319036536,
          "lon" : 60.6148520947
        }
      },
      "lastUpdate" : "20160319T041229Z",
      "date" : "20160319"
    }
  }, {
    "type" : "Feature",
    "geometry" : {
      "type" : "Point",
      "coordinates" : [ 60.58612623391936, 56.82947461635581 ]
    },
    "properties" : {
      "type" : "place",
      "startTime" : "20160319T095011+0600",
      "endTime" : "20160319T165636+0600",
      "place" : {
        "id" : 267526997,
        "name" : "СКБ Контур",
        "type" : "user",
        "location" : {
          "lat" : 56.82947461635581,
          "lon" : 60.58612623391936
        }
      },
      "lastUpdate" : "20160516T162957Z",
      "date" : "20160319"
    }
  }, {
    "type" : "Feature",
    "geometry" : {
      "type" : "Point",
      "coordinates" : [ 60.6149925827, 56.8313908867 ]
    },
    "properties" : {
      "type" : "place",
      "startTime" : "20160319T173252+0600",
      "endTime" : "20160320T101236+0600",
      "place" : {
        "id" : 280596482,
        "type" : "unknown",
        "location" : {
          "lat" : 56.8313908867,
          "lon" : 60.6149925827
        }
      },
      "lastUpdate" : "20160320T113258Z",
      "date" : "20160319"
    }
  } ]
}